tiff_utils/__init__.py
tiff_utils/_version.py
tiff_utils/tiff_utils.py
tiff_utils/_tests/__init__.py
tiff_utils/_tests/test_tiff_utils.py
tiff_utils-0.1.0.dist-info/LICENCE
tiff_utils-0.1.0.dist-info/METADATA
tiff_utils-0.1.0.dist-info/WHEEL
tiff_utils-0.1.0.dist-info/top_level.txt
tiff_utils-0.1.0.dist-info/RECORD
