Metadata-Version: 2.1
Name: tiff-utils
Version: 0.1.0
Summary: A class for easy manipulation of tiff files
Home-page: https://github.com/CBI-PITT/tiff_utils
Author: Alan M Watson
Author-email: alan.watson@pitt.edu
License: BSD-3-Clause
Project-URL: Bug Tracker, https://github.com/CBI-PITT/tiff_utils/issues
Project-URL: Documentation, https://github.com/CBI-PITT/tiff_utils#README.md
Project-URL: Source Code, https://github.com/CBI-PITT/tiff_utils
Project-URL: User Support, https://github.com/CBI-PITT/tiff_utils/issues
Platform: UNKNOWN
Classifier: Development Status :: 2 - Pre-Alpha
Classifier: Intended Audience :: Developers
Classifier: Topic :: Software Development :: Testing
Classifier: Programming Language :: Python
Classifier: Programming Language :: Python :: 3
Classifier: Programming Language :: Python :: 3.7
Classifier: Programming Language :: Python :: 3.8
Classifier: Programming Language :: Python :: 3.9
Classifier: Operating System :: OS Independent
Classifier: License :: OSI Approved :: BSD License
Requires-Python: >=3.7
License-File: LICENCE
Requires-Dist: numpy
Requires-Dist: scikit-image
Requires-Dist: tifffile
